gisp/__init__.py
gisp/gisp.py
tests/__init__.py
tests/test_gisp.py
gisp-1.0.1.dist-info/LICENSE
gisp-1.0.1.dist-info/METADATA
gisp-1.0.1.dist-info/WHEEL
gisp-1.0.1.dist-info/top_level.txt
gisp-1.0.1.dist-info/RECORD
