Metadata-Version: 2.1
Name: gisp
Version: 1.0.1
Summary: Generalized Interval-extended Sequential Pattern mining
Home-page: https://github.com/wu0306109/gisp
Author: wu0306109
Author-email: t110598007@ntut.org.tw
Classifier: Programming Language :: Python :: 3
License-File: LICENSE
